anomalo/__init__.py
anomalo/__main__.py
anomalo/__version__.py
anomalo/anomalo.py
anomalo/cli/__init__.py
anomalo/cli/cli.py
anomalo/cli/save_load/__init__.py
anomalo/cli/save_load/commands.py
anomalo/cli/save_load/models.py
anomalo/cli/state/__init__.py
anomalo/cli/state/api.py
anomalo/cli/state/errors.py
anomalo/cli/state/file.py
anomalo/cli/state/machine.py
anomalo/cli/state/models.py
anomalo/cli/state/system_check.py
anomalo/client.py
anomalo/encoder.py
anomalo/result.py
anomalo-0.38.0.dist-info/LICENSE
anomalo-0.38.0.dist-info/METADATA
anomalo-0.38.0.dist-info/WHEEL
anomalo-0.38.0.dist-info/entry_points.txt
anomalo-0.38.0.dist-info/RECORD
